ports_v2_core/__init__.py
ports_v2_core/rpc/__init__.py
ports_v2_core/rpc/clients/__init__.py
ports_v2_core/rpc/clients/auth.py
ports_v2_core/rpc/clients/crypto.py
ports_v2_core/rpc/clients/user.py
ports_v2_core/rpc/errors/__init__.py
ports_v2_core/rpc/errors/auth.py
ports_v2_core/rpc/errors/crypto.py
ports_v2_core/rpc/errors/users.py
ports_v2_core/schemas/__init__.py
ports_v2_core/schemas/users.py
ports_v2_core-0.1.9.dist-info/WHEEL
ports_v2_core-0.1.9.dist-info/METADATA
ports_v2_core-0.1.9.dist-info/RECORD
