Metadata-Version: 2.1
Name: ports-v2-core
Version: 0.1.9
Summary: 
Author: Your Name
Author-email: you@example.com
Requires-Python: >=3.10,<4.0
Classifier: Programming Language :: Python :: 3
Classifier: Programming Language :: Python :: 3.10
Requires-Dist: fastapi-jsonrpc (>=2.2.2,<3.0.0)
Requires-Dist: jsonrpcclient (>=4.0.2,<5.0.0)
Requires-Dist: pydantic[email] (>=1.9.1,<2.0.0)
Requires-Dist: python-dotenv (>=0.20.0,<0.21.0)
Requires-Dist: requests (>=2.28.1,<3.0.0)
